{
  "frontmatter-系统/": {
    "valueHash": "2dc0d2611b57b47ab989f9a492280663",
    "isUserSet": false,
    "isActiveInStructure": false
  },
  "_self_": {
    "valueHash": "2dc0d2611b57b47ab989f9a492280663",
    "isUserSet": false,
    "isActiveInStructure": true
  },
  "content-and-ui.md": {
    "valueHash": "f6c0817d841ce39e245113aa41d8633b",
    "isUserSet": false,
    "isActiveInStructure": false
  },
  "global-page.md": {
    "valueHash": "a8b99e584417319210566fbe3ce201d5",
    "isUserSet": false,
    "isActiveInStructure": false
  },
  "features-and-home.md": {
    "valueHash": "8fdf140888dbe299c06dd8220dda7d9f",
    "isUserSet": false,
    "isActiveInStructure": false
  },
  "sidebar-auto-system.md": {
    "valueHash": "893be3f7e576a00c0347f88daf682ffd",
    "isUserSet": false,
    "isActiveInStructure": false
  },
  "key-inventory.md": {
    "valueHash": "4b0a42fbbacfb87d8cb9dbd390597611",
    "isUserSet": false,
    "isActiveInStructure": false
  },
  "hero-runtime.md": {
    "valueHash": "6049106e1a4cd09bc0f790092f76ae89",
    "isUserSet": false,
    "isActiveInStructure": false
  },
  "content/": {
    "valueHash": "9a0364b9e99bb480dd25e1f0284c8555",
    "isUserSet": false,
    "isActiveInStructure": true
  },
  "hero/": {
    "valueHash": "f04af61b3f332afa0ceec786a42cd365",
    "isUserSet": false,
    "isActiveInStructure": true
  },
  "page/": {
    "valueHash": "71860c77c6745379b0d44304d66b6a13",
    "isUserSet": false,
    "isActiveInStructure": true
  },
  "reference/": {
    "valueHash": "b8af13ea9c8fe890c9979a1fa8dbde22",
    "isUserSet": false,
    "isActiveInStructure": true
  }
}